.gitignore
CHANGES.rst
LICENSE.rst
MANIFEST.in
README.rst
bower.json
setup.cfg
setup.py
js/__init__.py
js.bootstrap_image_gallery.egg-info/PKG-INFO
js.bootstrap_image_gallery.egg-info/SOURCES.txt
js.bootstrap_image_gallery.egg-info/dependency_links.txt
js.bootstrap_image_gallery.egg-info/entry_points.txt
js.bootstrap_image_gallery.egg-info/namespace_packages.txt
js.bootstrap_image_gallery.egg-info/not-zip-safe
js.bootstrap_image_gallery.egg-info/requires.txt
js.bootstrap_image_gallery.egg-info/top_level.txt
js/bootstrap_image_gallery/__init__.py
js/bootstrap_image_gallery/test_bootstrap_image_gallery.txt
js/bootstrap_image_gallery/resources/.DS_Store
js/bootstrap_image_gallery/resources/blueimp-bootstrap-image-gallery/css/bootstrap-image-gallery.css
js/bootstrap_image_gallery/resources/blueimp-bootstrap-image-gallery/css/bootstrap-image-gallery.min.css
js/bootstrap_image_gallery/resources/blueimp-bootstrap-image-gallery/img/loading.gif
js/bootstrap_image_gallery/resources/blueimp-bootstrap-image-gallery/js/bootstrap-image-gallery.js
js/bootstrap_image_gallery/resources/blueimp-bootstrap-image-gallery/js/bootstrap-image-gallery.min.js
js/bootstrap_image_gallery/resources/blueimp-gallery/css/blueimp-gallery-indicator.css
js/bootstrap_image_gallery/resources/blueimp-gallery/css/blueimp-gallery-video.css
js/bootstrap_image_gallery/resources/blueimp-gallery/css/blueimp-gallery.css
js/bootstrap_image_gallery/resources/blueimp-gallery/css/blueimp-gallery.min.css
js/bootstrap_image_gallery/resources/blueimp-gallery/img/error.png
js/bootstrap_image_gallery/resources/blueimp-gallery/img/error.svg
js/bootstrap_image_gallery/resources/blueimp-gallery/img/loading.gif
js/bootstrap_image_gallery/resources/blueimp-gallery/img/play-pause.png
js/bootstrap_image_gallery/resources/blueimp-gallery/img/play-pause.svg
js/bootstrap_image_gallery/resources/blueimp-gallery/img/video-play.png
js/bootstrap_image_gallery/resources/blueimp-gallery/img/video-play.svg
js/bootstrap_image_gallery/resources/blueimp-gallery/js/blueimp-gallery-fullscreen.js
js/bootstrap_image_gallery/resources/blueimp-gallery/js/blueimp-gallery-indicator.js
js/bootstrap_image_gallery/resources/blueimp-gallery/js/blueimp-gallery-video.js
js/bootstrap_image_gallery/resources/blueimp-gallery/js/blueimp-gallery-vimeo.js
js/bootstrap_image_gallery/resources/blueimp-gallery/js/blueimp-gallery-youtube.js
