Metadata-Version: 1.0
Name: js.bootstrap-image-gallery
Version: 3.1.1-1
Summary: Fanstatic packaging of Bootstrap Image Gallery
Home-page: https://github.com/disko/js.bootstrap_image_gallery
Author: Andreas Kaiser
Author-email: disko@binary-punks.com
License: BSD
Platform: UNKNOWN
